[
    {
        "type": 1,
        "decoName": 6500001,
        "desc": 6510001,
        "xSize": 1,
        "ySize": 2,
        "action": 0,
        "actionRate": 0,
        "class": 0,
        "image": "base_resource_1x2_001",
        "thumbnail": "base_icon_1x2_001",
        "atlasNumber": 1,
        "fixedSkin": 0,
        "decoIdx": 0
    },
    {
        "type": 2,
        "decoName": 6500002,
        "desc": 6510002,
        "xSize": 1,
        "ySize": 2,
        "action": 0,
        "actionRate": 0,
        "class": 0,
        "image": "base_resource_1x2_002",
        "thumbnail": "base_icon_1x2_002",
        "atlasNumber": 1,
        "fixedSkin": 0,
        "decoIdx": 0
    },
    {
        "type": 3,
        "decoName": 6500003,
        "desc": 6510003,
        "xSize": 2,
        "ySize": 3,
        "action": 1,
        "actionRate": 90,
        "class": 0,
        "image": "base_resource_2x3_003",
        "thumbnail": "base_icon_2x3_003",
        "atlasNumber": 1,
        "fixedSkin": 0,
        "decoIdx": 0
    },
    {
        "type": 4,
        "decoName": 6500004,
        "desc": 6510004,
        "xSize": 1,
        "ySize": 2,
        "action": 0,
        "actionRate": 0,
        "class": 0,
        "image": "thema001_resource_1x2_001",
        "thumbnail": "thema001_icon_1x2_001",
        "atlasNumber": 1,
        "fixedSkin": 0,
        "decoIdx": 0
    },
    {
        "type": 5,
        "decoName": 6500005,
        "desc": 6510005,
        "xSize": 1,
        "ySize": 2,
        "action": 1,
        "actionRate": 90,
        "class": 0,
        "image": "thema001_resource_1x2_002",
        "thumbnail": "thema001_icon_1x2_002",
        "atlasNumber": 1,
        "fixedSkin": 0,
        "decoIdx": 0
    },
    {
        "type": 6,
        "decoName": 6500006,
        "desc": 6510006,
        "xSize": 1,
        "ySize": 2,
        "action": 0,
        "actionRate": 0,
        "class": 0,
        "image": "thema001_resource_1x2_003",
        "thumbnail": "thema001_icon_1x2_003",
        "atlasNumber": 1,
        "fixedSkin": 0,
        "decoIdx": 0
    },
    {
        "type": 7,
        "decoName": 6500007,
        "desc": 6510007,
        "xSize": 1,
        "ySize": 2,
        "action": 0,
        "actionRate": 0,
        "class": 0,
        "image": "thema001_resource_1x2_004",
        "thumbnail": "thema001_icon_1x2_004",
        "atlasNumber": 1,
        "fixedSkin": 0,
        "decoIdx": 0
    },
    {
        "type": 8,
        "decoName": 6500008,
        "desc": 6510008,
        "xSize": 2,
        "ySize": 2,
        "action": 0,
        "actionRate": 0,
        "class": 0,
        "image": "thema001_resource_2x2_005",
        "thumbnail": "thema001_icon_2x2_005",
        "atlasNumber": 1,
        "fixedSkin": 0,
        "decoIdx": 0
    },
    {
        "type": 9,
        "decoName": 6500009,
        "desc": 6510009,
        "xSize": 2,
        "ySize": 2,
        "action": 0,
        "actionRate": 0,
        "class": 0,
        "image": "thema001_resource_2x2_006",
        "thumbnail": "thema001_icon_2x2_006",
        "atlasNumber": 1,
        "fixedSkin": 0,
        "decoIdx": 0
    },
    {
        "type": 10,
        "decoName": 6500010,
        "desc": 6510010,
        "xSize": 2,
        "ySize": 2,
        "action": 1,
        "actionRate": 90,
        "class": 1,
        "image": "thema001_resource_2x2_007",
        "thumbnail": "thema001_icon_2x2_007",
        "atlasNumber": 1,
        "fixedSkin": 0,
        "decoIdx": 0
    },
    {
        "type": 11,
        "decoName": 6500011,
        "desc": 6510011,
        "xSize": 2,
        "ySize": 3,
        "action": 0,
        "actionRate": 0,
        "class": 0,
        "image": "thema001_resource_2x3_008",
        "thumbnail": "thema001_icon_2x3_008",
        "atlasNumber": 1,
        "fixedSkin": 0,
        "decoIdx": 0
    },
    {
        "type": 12,
        "decoName": 6500012,
        "desc": 6510012,
        "xSize": 2,
        "ySize": 3,
        "action": 1,
        "actionRate": 90,
        "class": 0,
        "image": "thema001_resource_2x3_009",
        "thumbnail": "thema001_icon_2x3_009",
        "atlasNumber": 1,
        "fixedSkin": 0,
        "decoIdx": 0
    },
    {
        "type": 13,
        "decoName": 6500013,
        "desc": 6510013,
        "xSize": 3,
        "ySize": 3,
        "action": 0,
        "actionRate": 0,
        "class": 0,
        "image": "thema001_resource_3x3_010",
        "thumbnail": "thema001_icon_3x3_010",
        "atlasNumber": 1,
        "fixedSkin": 0,
        "decoIdx": 0
    },
    {
        "type": 14,
        "decoName": 6500014,
        "desc": 6510014,
        "xSize": 1,
        "ySize": 2,
        "action": 0,
        "actionRate": 0,
        "class": 0,
        "image": "thema002_resource_1x2_001",
        "thumbnail": "thema002_icon_1x2_001",
        "atlasNumber": 1,
        "fixedSkin": 0,
        "decoIdx": 0
    },
    {
        "type": 15,
        "decoName": 6500015,
        "desc": 6510015,
        "xSize": 1,
        "ySize": 2,
        "action": 1,
        "actionRate": 90,
        "class": 0,
        "image": "thema002_resource_1x2_002",
        "thumbnail": "thema002_icon_1x2_002",
        "atlasNumber": 1,
        "fixedSkin": 0,
        "decoIdx": 0
    },
    {
        "type": 16,
        "decoName": 6500016,
        "desc": 6510016,
        "xSize": 1,
        "ySize": 2,
        "action": 0,
        "actionRate": 0,
        "class": 0,
        "image": "thema002_resource_1x2_003",
        "thumbnail": "thema002_icon_1x2_003",
        "atlasNumber": 1,
        "fixedSkin": 0,
        "decoIdx": 0
    },
    {
        "type": 17,
        "decoName": 6500017,
        "desc": 6510017,
        "xSize": 1,
        "ySize": 2,
        "action": 0,
        "actionRate": 0,
        "class": 0,
        "image": "thema002_resource_1x2_004",
        "thumbnail": "thema002_icon_1x2_004",
        "atlasNumber": 1,
        "fixedSkin": 0,
        "decoIdx": 0
    },
    {
        "type": 18,
        "decoName": 6500018,
        "desc": 6510018,
        "xSize": 2,
        "ySize": 2,
        "action": 0,
        "actionRate": 0,
        "class": 0,
        "image": "thema002_resource_2x2_005",
        "thumbnail": "thema002_icon_2x2_005",
        "atlasNumber": 1,
        "fixedSkin": 0,
        "decoIdx": 0
    },
    {
        "type": 19,
        "decoName": 6500019,
        "desc": 6510019,
        "xSize": 2,
        "ySize": 2,
        "action": 0,
        "actionRate": 0,
        "class": 0,
        "image": "thema002_resource_2x2_006",
        "thumbnail": "thema002_icon_2x2_006",
        "atlasNumber": 1,
        "fixedSkin": 0,
        "decoIdx": 0
    },
    {
        "type": 20,
        "decoName": 6500020,
        "desc": 6510020,
        "xSize": 2,
        "ySize": 3,
        "action": 1,
        "actionRate": 90,
        "class": 1,
        "image": "thema002_resource_2x3_007",
        "thumbnail": "thema002_icon_2x3_007",
        "atlasNumber": 1,
        "fixedSkin": 1,
        "decoIdx": 0
    },
    {
        "type": 21,
        "decoName": 6500021,
        "desc": 6510021,
        "xSize": 3,
        "ySize": 2,
        "action": 0,
        "actionRate": 0,
        "class": 0,
        "image": "thema002_resource_2x3_008",
        "thumbnail": "thema002_icon_2x3_008",
        "atlasNumber": 1,
        "fixedSkin": 0,
        "decoIdx": 0
    },
    {
        "type": 22,
        "decoName": 6500022,
        "desc": 6510022,
        "xSize": 2,
        "ySize": 3,
        "action": 0,
        "actionRate": 0,
        "class": 0,
        "image": "thema002_resource_2x3_009",
        "thumbnail": "thema002_icon_2x3_009",
        "atlasNumber": 1,
        "fixedSkin": 0,
        "decoIdx": 0
    },
    {
        "type": 23,
        "decoName": 6500023,
        "desc": 6510023,
        "xSize": 3,
        "ySize": 3,
        "action": 0,
        "actionRate": 0,
        "class": 0,
        "image": "thema002_resource_3x3_010",
        "thumbnail": "thema002_icon_3x3_010",
        "atlasNumber": 1,
        "fixedSkin": 0,
        "decoIdx": 0
    },
    {
        "type": 24,
        "decoName": 6500024,
        "desc": 6510024,
        "xSize": 1,
        "ySize": 2,
        "action": 0,
        "actionRate": 0,
        "class": 0,
        "image": "thema003_resource_1x2_001",
        "thumbnail": "thema003_icon_1x2_001",
        "atlasNumber": 1,
        "fixedSkin": 0,
        "decoIdx": 0
    },
    {
        "type": 25,
        "decoName": 6500025,
        "desc": 6510025,
        "xSize": 1,
        "ySize": 2,
        "action": 1,
        "actionRate": 90,
        "class": 0,
        "image": "thema003_resource_1x2_002",
        "thumbnail": "thema003_icon_1x2_002",
        "atlasNumber": 1,
        "fixedSkin": 0,
        "decoIdx": 0
    },
    {
        "type": 26,
        "decoName": 6500026,
        "desc": 6510026,
        "xSize": 1,
        "ySize": 2,
        "action": 0,
        "actionRate": 0,
        "class": 0,
        "image": "thema003_resource_1x2_003",
        "thumbnail": "thema003_icon_1x2_003",
        "atlasNumber": 1,
        "fixedSkin": 0,
        "decoIdx": 0
    },
    {
        "type": 27,
        "decoName": 6500027,
        "desc": 6510027,
        "xSize": 1,
        "ySize": 2,
        "action": 0,
        "actionRate": 0,
        "class": 0,
        "image": "thema003_resource_1x2_004",
        "thumbnail": "thema003_icon_1x2_004",
        "atlasNumber": 1,
        "fixedSkin": 0,
        "decoIdx": 0
    },
    {
        "type": 28,
        "decoName": 6500028,
        "desc": 6510028,
        "xSize": 2,
        "ySize": 2,
        "action": 0,
        "actionRate": 0,
        "class": 0,
        "image": "thema003_resource_2x2_005",
        "thumbnail": "thema003_icon_2x2_005",
        "atlasNumber": 1,
        "fixedSkin": 0,
        "decoIdx": 0
    },
    {
        "type": 29,
        "decoName": 6500029,
        "desc": 6510029,
        "xSize": 2,
        "ySize": 2,
        "action": 0,
        "actionRate": 0,
        "class": 0,
        "image": "thema003_resource_2x2_006",
        "thumbnail": "thema003_icon_2x2_006",
        "atlasNumber": 1,
        "fixedSkin": 0,
        "decoIdx": 0
    },
    {
        "type": 30,
        "decoName": 6500030,
        "desc": 6510030,
        "xSize": 2,
        "ySize": 2,
        "action": 1,
        "actionRate": 90,
        "class": 1,
        "image": "thema003_resource_2x2_007",
        "thumbnail": "thema003_icon_2x2_007",
        "atlasNumber": 1,
        "fixedSkin": 0,
        "decoIdx": 1
    },
    {
        "type": 31,
        "decoName": 6500031,
        "desc": 6510031,
        "xSize": 2,
        "ySize": 2,
        "action": 0,
        "actionRate": 0,
        "class": 0,
        "image": "thema003_resource_2x2_008",
        "thumbnail": "thema003_icon_2x2_008",
        "atlasNumber": 1,
        "fixedSkin": 0,
        "decoIdx": 0
    },
    {
        "type": 32,
        "decoName": 6500032,
        "desc": 6510032,
        "xSize": 2,
        "ySize": 3,
        "action": 1,
        "actionRate": 90,
        "class": 0,
        "image": "thema003_resource_2x3_009",
        "thumbnail": "thema003_icon_2x3_009",
        "atlasNumber": 1,
        "fixedSkin": 0,
        "decoIdx": 0
    },
    {
        "type": 33,
        "decoName": 6500033,
        "desc": 6510033,
        "xSize": 2,
        "ySize": 3,
        "action": 0,
        "actionRate": 0,
        "class": 0,
        "image": "thema003_resource_2x3_010",
        "thumbnail": "thema003_icon_2x3_010",
        "atlasNumber": 1,
        "fixedSkin": 0,
        "decoIdx": 0
    },
    {
        "type": 34,
        "decoName": 6500034,
        "desc": 6510034,
        "xSize": 1,
        "ySize": 2,
        "action": 0,
        "actionRate": 0,
        "class": 0,
        "image": "thema004_resource_1x2_001",
        "thumbnail": "thema004_icon_1x2_001",
        "atlasNumber": 1,
        "fixedSkin": 0,
        "decoIdx": 0
    },
    {
        "type": 35,
        "decoName": 6500035,
        "desc": 6510035,
        "xSize": 1,
        "ySize": 2,
        "action": 1,
        "actionRate": 90,
        "class": 0,
        "image": "thema004_resource_1x2_002",
        "thumbnail": "thema004_icon_1x2_004",
        "atlasNumber": 1,
        "fixedSkin": 0,
        "decoIdx": 0
    },
    {
        "type": 36,
        "decoName": 6500036,
        "desc": 6510036,
        "xSize": 1,
        "ySize": 2,
        "action": 0,
        "actionRate": 0,
        "class": 0,
        "image": "thema004_resource_1x2_003",
        "thumbnail": "thema004_icon_1x2_003",
        "atlasNumber": 1,
        "fixedSkin": 0,
        "decoIdx": 0
    },
    {
        "type": 37,
        "decoName": 6500037,
        "desc": 6510037,
        "xSize": 1,
        "ySize": 2,
        "action": 0,
        "actionRate": 0,
        "class": 0,
        "image": "thema004_resource_1x2_004",
        "thumbnail": "thema004_icon_1x2_002",
        "atlasNumber": 1,
        "fixedSkin": 0,
        "decoIdx": 0
    },
    {
        "type": 38,
        "decoName": 6500038,
        "desc": 6510038,
        "xSize": 2,
        "ySize": 2,
        "action": 0,
        "actionRate": 0,
        "class": 0,
        "image": "thema004_resource_2x2_005",
        "thumbnail": "thema004_icon_2x2_005",
        "atlasNumber": 1,
        "fixedSkin": 0,
        "decoIdx": 0
    },
    {
        "type": 39,
        "decoName": 6500039,
        "desc": 6510039,
        "xSize": 2,
        "ySize": 2,
        "action": 0,
        "actionRate": 0,
        "class": 0,
        "image": "thema004_resource_2x2_006",
        "thumbnail": "thema004_icon_2x2_006",
        "atlasNumber": 1,
        "fixedSkin": 0,
        "decoIdx": 0
    },
    {
        "type": 40,
        "decoName": 6500040,
        "desc": 6510040,
        "xSize": 3,
        "ySize": 3,
        "action": 1,
        "actionRate": 90,
        "class": 1,
        "image": "thema004_resource_3x3_007",
        "thumbnail": "thema004_icon_3x3_007",
        "atlasNumber": 1,
        "fixedSkin": 0,
        "decoIdx": 2
    },
    {
        "type": 41,
        "decoName": 6500041,
        "desc": 6510041,
        "xSize": 2,
        "ySize": 3,
        "action": 0,
        "actionRate": 0,
        "class": 0,
        "image": "thema004_resource_2x3_008",
        "thumbnail": "thema004_icon_2x3_008",
        "atlasNumber": 1,
        "fixedSkin": 0,
        "decoIdx": 0
    },
    {
        "type": 42,
        "decoName": 6500042,
        "desc": 6510042,
        "xSize": 2,
        "ySize": 3,
        "action": 1,
        "actionRate": 90,
        "class": 0,
        "image": "thema004_resource_2x3_009",
        "thumbnail": "thema004_icon_2x3_009",
        "atlasNumber": 1,
        "fixedSkin": 0,
        "decoIdx": 0
    }
]